telegram_news/__init__.py
telegram_news/displaypolicy.py
telegram_news/table.sql
telegram_news/utils.py
telegram_news/template/__init__.py
telegram_news/template/common.py
telegram_news_eswzy-0.0.6.dist-info/LICENSE
telegram_news_eswzy-0.0.6.dist-info/METADATA
telegram_news_eswzy-0.0.6.dist-info/WHEEL
telegram_news_eswzy-0.0.6.dist-info/top_level.txt
telegram_news_eswzy-0.0.6.dist-info/RECORD
